test_maturin_cedar-0.1.2.dist-info/METADATA
test_maturin_cedar-0.1.2.dist-info/WHEEL
test_maturin_cedar-0.1.2.dist-info/license_files/LICENSE
test_maturin_cedar/lib.py
test_maturin_cedar/py.typed
test_maturin_cedar/test_maturin_cedar.pyi
test_maturin_cedar/__init__.py
test_maturin_cedar/test_maturin_cedar.cp312-win_amd64.pyd
test_maturin_cedar-0.1.2.dist-info/RECORD
