Metadata-Version: 2.1
Name: test-maturin-cedar
Version: 0.1.2
Classifier: Programming Language :: Rust
Classifier: Programming Language :: Python :: Implementation :: CPython
Classifier: Programming Language :: Python :: Implementation :: PyPy
License-File: LICENSE
Summary: cedar-policy bindings
Author-email: Naoya Yamashita <conao3@gmail.com>
License: Apache-2.0
Requires-Python: >=3.12
